setup.py
mdscript/__init__.py
mdscript/base_transformer.py
mdscript/cli.py
mdscript/config.py
mdscript/example.py
mdscript/files_dependencies_manager.py
mdscript/runner.py
mdscript/setup.py
mdscript/watcher.py
mdscript.egg-info/PKG-INFO
mdscript.egg-info/SOURCES.txt
mdscript.egg-info/dependency_links.txt
mdscript.egg-info/requires.txt
mdscript.egg-info/top_level.txt
mdscript/transformers/__init__.py
mdscript/transformers/file_import_transformer.py
mdscript/transformers/structnosql_sample_transformer.py
mdscript/transformers/table_transformer.py