Metadata-Version: 1.0
Name: mdscript
Version: 0.1.3.1
Summary: Brings powerful scripting to markdown files with hot reload
Home-page: https://github.com/Robinson04/mdscript
Author: Inoft
Author-email: robinson@inoft.com
License: MIT
Platform: UNKNOWN
